gpt_address_api
