Metadata-Version: 2.1
Name: gpt-address-api
Version: 0.1.1
Summary: Decentralized GPT API for everyone !
Home-page: https://github.com/Naruno/GPT-Address-API
Author: Naruno Developers
Author-email: onur.atakan.ulusoy@naruno.org
License: MIT
Platform: UNKNOWN
Requires-Python: >= 3
